nbt2yaml/__init__.py
nbt2yaml/compat.py
nbt2yaml/main.py
nbt2yaml/parse.py
nbt2yaml/yamlgen.py
nbt2yaml-0.4.2.dist-info/LICENSE
nbt2yaml-0.4.2.dist-info/METADATA
nbt2yaml-0.4.2.dist-info/WHEEL
nbt2yaml-0.4.2.dist-info/entry_points.txt
nbt2yaml-0.4.2.dist-info/top_level.txt
nbt2yaml-0.4.2.dist-info/RECORD
