Metadata-Version: 2.1
Name: nbt2yaml
Version: 0.4.2
Summary: Read and write Minecraft NBT files using Yaml.
Home-page: https://github.com/zzzeek/nbt2yaml
Author: Mike Bayer
Author-email: mike_mp@zzzcomputing.com
License: MIT
Project-URL: Issue Tracker, https://github.com/zzzeek/nbt2yaml
Keywords: Minecraft
Platform: UNKNOWN
Classifier: Development Status :: 3 - Alpha
Classifier: Intended Audience :: Developers
Classifier: License :: OSI Approved :: MIT License
Classifier: Programming Language :: Python
Classifier: Programming Language :: Python :: 3
License-File: LICENSE
Requires-Dist: PyYAML (>=5.1)
Requires-Dist: python-editor (>=0.3)
